{
  "en": {
    "welcome": "Welcome to MedBridge+",
    "select_language": "Choose Your Language",
    "next": "Next",
    "back": "Back",
    "submit": "Submit",
    "step_1": "Select Body Area",
    "step_2": "Select Symptom Type",
    "step_3": "Severity",
    "step_4": "Duration",
    "step_5": "Associated Symptoms",
    "step_6": "Additional Notes",
    "head": "Head",
    "chest": "Chest",
    "abdomen": "Abdomen",
    "throat": "Throat",
    "back": "Back",
    "limbs": "Limbs",
    "pain": "Pain",
    "fever": "Fever",
    "cough": "Cough",
    "vomiting": "Vomiting",
    "breathlessness": "Breathlessness",
    "dizziness": "Dizziness",
    "mild": "Mild",
    "moderate": "Moderate",
    "severe": "Severe",
    "today": "Today",
    "1_2_days": "1–2 days",
    "3_7_days": "3–7 days",
    "plus_1_week": ">1 week",
    "weakness": "Weakness",
    "bleeding": "Bleeding",
    "summary_title": "Doctor Summary Card",
    "priority": "Priority",
    "low": "LOW",
    "mod": "MODERATE",
    "high": "HIGH",
    "red_flag": "Red Flag",
    "yes": "Yes",
    "no": "No",
    "view_history": "View History",
    "new_intake": "New Intake"
  },
  "hi": {
    "welcome": "MedBridge+ में आपका स्वागत है",
    "select_language": "अपनी भाषा चुनें",
    "next": "अगला",
    "back": "पीछे",
    "submit": "जमा करें",
    "step_1": "शरीर का क्षेत्र चुनें",
    "step_2": "लक्षण का प्रकार चुनें",
    "step_3": "तीव्रता",
    "step_4": "अवधि",
    "step_5": "जुड़े हुए लक्षण",
    "step_6": "अतिरिक्त नोट्स",
    "head": "सिर",
    "chest": "छाती",
    "abdomen": "पेट",
    "throat": "गला",
    "back": "पीठ",
    "limbs": "अंग",
    "pain": "दर्द",
    "fever": "बुखार",
    "cough": "खांसी",
    "vomiting": "उल्टी",
    "breathlessness": "सांस फूलना",
    "dizziness": "चक्कर आना",
    "mild": "हल्का",
    "moderate": "मध्यम",
    "severe": "गंभीर",
    "today": "आज",
    "1_2_days": "1-2 दिन",
    "3_7_days": "3-7 दिन",
    "plus_1_week": ">1 सप्ताह",
    "weakness": "कमजोरी",
    "bleeding": "रक्तस्राव",
    "summary_title": "डॉक्टर सारांश कार्ड",
    "priority": "प्राथमिकता",
    "low": "कम",
    "mod": "मध्यम",
    "high": "उच्च",
    "red_flag": "खतरे का निशान",
    "yes": "हाँ",
    "no": "नहीं",
    "view_history": "इतिहास देखें",
    "new_intake": "नई जांच"
  },
  "te": {
    "welcome": "MedBridge+ కి స్వాగతం",
    "select_language": "మీ భాషను ఎంచుకోండి",
    "next": "తదుపరి",
    "back": "వెనుకకు",
    "submit": "సమర్పించండి",
    "step_1": "శరీర భాగాన్ని ఎంచుకోండి",
    "step_2": "లక్షణ రకాన్ని ఎంచుకోండి",
    "step_3": "తీవ్రత",
    "step_4": "వ్యవధి",
    "step_5": "సంబంధిత లక్షణాలు",
    "step_6": "అదనపు గమనికలు",
    "head": "తల",
    "chest": "ఛాతీ",
    "abdomen": "కడుపు",
    "throat": "గొంతు",
    "back": "వెన్ను",
    "limbs": "కాళ్లు చేతులు",
    "pain": "నొప్పి",
    "fever": "జ్వరం",
    "cough": "దగ్గు",
    "vomiting": "వాంతులు",
    "breathlessness": "ఆయాసం",
    "dizziness": "కళ్ళు తిరగడం",
    "mild": "తక్కువ",
    "moderate": "మధ్యస్థం",
    "severe": "ఎక్కువ",
    "today": "ఈ రోజు",
    "1_2_days": "1–2 రోజులు",
    "3_7_days": "3–7 రోజులు",
    "plus_1_week": ">1 వారం",
    "weakness": "నీరసం",
    "bleeding": "రక్తస్రావం",
    "summary_title": "డాక్టర్ సారాంశం కార్డ్",
    "priority": "ప్రాధాన్యత",
    "low": "తక్కువ",
    "mod": "మధ్యస్థం",
    "high": "ఎక్కువ",
    "red_flag": "ప్రమాద సూచిక",
    "yes": "అవును",
    "no": "కాదు",
    "view_history": "చరిత్రను చూడండి",
    "new_intake": "కొత్తది"
  },
  "ta": {
    "welcome": "MedBridge+ க்கு வரவேற்கிறோம்",
    "select_language": "உங்கள் மொழியைத் தேர்ந்தெடுக்கவும்",
    "next": "அடுத்து",
    "back": "பின்னால்",
    "submit": "சமர்ப்பிக்கவும்",
    "step_1": "உடல் பகுதியைத் தேர்ந்தெடுக்கவும்",
    "step_2": "அறிகுறி வகையைத் தேர்ந்தெடுக்கவும்",
    "step_3": "தீவிரத்தன்மை",
    "step_4": "கால அளவு",
    "step_5": "தொடர்புடைய அறிகுறிகள்",
    "step_6": "கூடுதல் குறிப்புகள்",
    "head": "தலை",
    "chest": "நெஞ்சு",
    "abdomen": "வயிறு",
    "throat": "தொண்டை",
    "back": "முதுகு",
    "limbs": "கை கால்கள்",
    "pain": "வலி",
    "fever": "காய்ச்சல்",
    "cough": "இருமல்",
    "vomiting": "வாந்தி",
    "breathlessness": "மூச்சுத்திணறல்",
    "dizziness": "தலைச்சுற்றல்",
    "mild": "மிதமான",
    "moderate": "நடுத்தர",
    "severe": "கடுமையான",
    "today": "இன்று",
    "1_2_days": "1-2 நாட்கள்",
    "3_7_days": "3-7 நாட்கள்",
    "plus_1_week": ">1 வாரம்",
    "weakness": "பலவீனம்",
    "bleeding": "இரத்தப்போக்கு",
    "summary_title": "மருத்துவர் சுருக்க அட்டை",
    "priority": "முன்னுரிமை",
    "low": "குறைந்த",
    "mod": "நடுத்தர",
    "high": "அதிக",
    "red_flag": "ஆபத்து அறிகுறி",
    "yes": "ஆம்",
    "no": "இல்லை",
    "view_history": "வரலாற்றைப் பார்க்கவும்",
    "new_intake": "புதிய பதிவு"
  },
  "bn": {
    "welcome": "MedBridge+ এ আপনাকে স্বাগতম",
    "select_language": "আপনার ভাষা চয়ন করুন",
    "next": "পরবর্তী",
    "back": "পিছনে",
    "submit": "জমা দিন",
    "step_1": "শরীরের অংশ নির্বাচন করুন",
    "step_2": "লক্ষণ নির্বাচন করুন",
    "step_3": "তীব্রতা",
    "step_4": "সময়কাল",
    "step_5": "সংশ্লিষ্ট লক্ষণ",
    "step_6": "অতিরিক্ত তথ্য",
    "head": "মাথা",
    "chest": "বুক",
    "abdomen": "পেট",
    "throat": "গলা",
    "back": "পিঠ",
    "limbs": "হাত-পা",
    "pain": "ব্যথা",
    "fever": "জ্বর",
    "cough": "কাশি",
    "vomiting": "বমি",
    "breathlessness": "শ্বাসকষ্ট",
    "dizziness": "মাথা ঘোরা",
    "mild": "সামান্য",
    "moderate": "মাঝারি",
    "severe": "তীব্র",
    "today": "আজ",
    "1_2_days": "১-২ দিন",
    "3_7_days": "৩-৭ দিন",
    "plus_1_week": ">১ সপ্তাহ",
    "weakness": "দুর্বলতা",
    "bleeding": "রক্তপাত",
    "summary_title": "ডাক্তারের সারাংশ কার্ড",
    "priority": "অগ্রাধিকার",
    "low": "কম",
    "mod": "মাঝারি",
    "high": "উচ্চ",
    "red_flag": "বিপদের লক্ষণ",
    "yes": "হ্যাঁ",
    "no": "না",
    "view_history": "ইতিহাস দেখুন",
    "new_intake": "নতুন এন্ট্রি"
  }
}
